{
    "posts": [
        {
            "title": "The Three Bosses of SEO",
            "link": "https://feedpress.me/link/9375/14742542/three-seo-bosses",
            "date": "2025-04-15T06:26:50.958024"
        },
        {
            "title": "The Three Bosses of SEO",
            "link": "https://feedpress.me/link/9375/14742542/three-seo-bosses",
            "date": "2025-04-15T06:26:50.959863"
        },
        {
            "title": "How to Calculate Your SEO ROI Using Google Analytics",
            "link": "https://feedpress.me/link/9375/14733670/calculate-seo-roi-with-google-analytics",
            "date": "2025-04-15T06:26:50.961858"
        },
        {
            "title": "How to Calculate Your SEO ROI Using Google Analytics",
            "link": "https://feedpress.me/link/9375/14733670/calculate-seo-roi-with-google-analytics",
            "date": "2025-04-15T06:26:50.964057"
        },
        {
            "title": "How to Use STAT to Find SEO Opportunities at Scale",
            "link": "https://feedpress.me/link/9375/14729254/find-seo-opportunities-with-stat",
            "date": "2025-04-15T06:26:50.965789"
        },
        {
            "title": "How to Use STAT to Find SEO Opportunities at Scale",
            "link": "https://feedpress.me/link/9375/14729254/find-seo-opportunities-with-stat",
            "date": "2025-04-15T06:26:50.967539"
        },
        {
            "title": "GEO, LLMO, AEO\u2026 It\u2019s All Just SEO",
            "link": "https://ahrefs.com/blog/geo-is-just-seo/",
            "date": "2025-04-15T06:26:50.969742"
        },
        {
            "title": "GEO, LLMO, AEO\u2026 It\u2019s All Just SEO",
            "link": "https://ahrefs.com/blog/geo-is-just-seo/",
            "date": "2025-04-15T06:26:50.972062"
        },
        {
            "title": "SEO for Financial Services: How to Build Trust and Rank Higher in 2025",
            "link": "https://ahrefs.com/blog/seo-for-financial-services/",
            "date": "2025-04-15T06:26:50.974349"
        },
        {
            "title": "SEO for Financial Services: How to Build Trust and Rank Higher in 2025",
            "link": "https://ahrefs.com/blog/seo-for-financial-services/",
            "date": "2025-04-15T06:26:50.976572"
        },
        {
            "title": "Python for SEO, Explained for Beginners",
            "link": "https://ahrefs.com/blog/python-for-seo/",
            "date": "2025-04-15T06:26:50.978898"
        },
        {
            "title": "Python for SEO, Explained for Beginners",
            "link": "https://ahrefs.com/blog/python-for-seo/",
            "date": "2025-04-15T06:26:50.981354"
        },
        {
            "title": "AI & SEO-Driven Content Marketing: How To Calculate True ROI for B2B Companies in 2025",
            "link": "https://www.searchenginejournal.com/ai-seo-content-b2b-heeet-spa/543662/",
            "date": "2025-04-15T06:26:51.008273"
        },
        {
            "title": "AI & SEO-Driven Content Marketing: How To Calculate True ROI for B2B Companies in 2025",
            "link": "https://www.searchenginejournal.com/ai-seo-content-b2b-heeet-spa/543662/",
            "date": "2025-04-15T06:26:51.010907"
        },
        {
            "title": "How To Apply E-E-A-T To Your Site & Boost On-Page SEO via @sejournal, @xandervalencia",
            "link": "https://www.searchenginejournal.com/on-page-seo/eat-ymyl/",
            "date": "2025-04-15T06:26:51.013509"
        },
        {
            "title": "How To Apply E-E-A-T To Your Site & Boost On-Page SEO via @sejournal, @xandervalencia",
            "link": "https://www.searchenginejournal.com/on-page-seo/eat-ymyl/",
            "date": "2025-04-15T06:26:51.015967"
        },
        {
            "title": "Wix\u2019s New AI Assistant Enables Meaningful Improvements To SEO, Sales And Productivity via @sejournal, @martinibuster",
            "link": "https://www.searchenginejournal.com/wixs-new-ai-assistant-enables-meaningful-improvements-to-seo-sales-and-productivity/544136/",
            "date": "2025-04-15T06:26:51.018659"
        },
        {
            "title": "Wix\u2019s New AI Assistant Enables Meaningful Improvements To SEO, Sales And Productivity via @sejournal, @martinibuster",
            "link": "https://www.searchenginejournal.com/wixs-new-ai-assistant-enables-meaningful-improvements-to-seo-sales-and-productivity/544136/",
            "date": "2025-04-15T06:26:51.021457"
        },
        {
            "title": "How to Do Keyword Research for SEO \u2014 Everything I Learned as a HubSpot Marketer",
            "link": "https://blog.hubspot.com/marketing/how-to-do-keyword-research-ht",
            "date": "2025-04-15T06:26:51.118275"
        },
        {
            "title": "How to Do Keyword Research for SEO \u2014 Everything I Learned as a HubSpot Marketer",
            "link": "https://blog.hubspot.com/marketing/how-to-do-keyword-research-ht",
            "date": "2025-04-15T06:26:51.213806"
        }
    ]
}